{
  "outlet": "11Alive (NBC Atlanta)",
  "outletLogo": "11alive",
  "category": "local-tv",
  "title": "Zac Brown Band's Coy Bowles Reads Children's Book Benefiting SOARD",
  "date": "2016-04-25",
  "url": "https://www.11alive.com/article/news/local/spoiled-kid-read-this-new-book-from-zac-brown-band-member/159494728",
  "excerpt": "11Alive studio appearance by Coy Bowles reading his children's book 'Will Powers,' with a portion of proceeds going to Sunshine on a Ranney Day.",
  "featured": false,
  "order": 17
}
