{
  "outlet": "Construction Resources",
  "outletLogo": "construction-resources",
  "category": "print",
  "title": "Transforming Lives: Sunshine on a Ranney Day and Construction Resources",
  "date": "2024-01-01",
  "url": "https://www.constructionresourcesusa.com/soard",
  "excerpt": "Construction Resources dedicated a feature page to the SOARD partnership, detailing the Howell Family makeover for three adopted special-needs children sponsored by Jackson Healthcare, plus their contribution to the Sunny & Ranney store build-out.",
  "featured": false,
  "order": 85
}
